cmdlr/__init__.py
cmdlr/amgr.py
cmdlr/analyzer.py
cmdlr/autil.py
cmdlr/cmdline.py
cmdlr/cmgr.py
cmdlr/conf.py
cmdlr/exception.py
cmdlr/info.py
cmdlr/jsona.py
cmdlr/log.py
cmdlr/merge.py
cmdlr/schema.py
cmdlr/yamla.py
cmdlr/analyzers/__init__.py
cmdlr/analyzers/cartoonmad.py
cmdlr/analyzers/manhuagui/__init__.py
cmdlr/analyzers/manhuagui/imgext.py
cmdlr/analyzers/manhuagui/infoext.py
cmdlr/analyzers/manhuagui/lz-string.min.js
cmdlr/analyzers/manhuagui/sharedjs.py
cmdlr/autil/__init__.py
cmdlr/autil/fetch.py
cmdlr/autil/jsproc.py
cmdlr/autil/useragent.json
cmdlr/autil/useragent.py
cmdlr/comic/__init__.py
cmdlr/comic/comic.py
cmdlr/comic/ifpool.py
cmdlr/comic/metatool.py
cmdlr/comic/volfile.py
cmdlr/infoprint/__init__.py
cmdlr/infoprint/azrinfo.py
cmdlr/infoprint/comicinfo.py
cmdlr/loopctrl/__init__.py
cmdlr/loopctrl/blueprint.py
cmdlr/loopctrl/chore.py
cmdlr/loopctrl/loopmgr.py
cmdlr/loopctrl/step.py
cmdlr/loopctrl/steprunner.py
cmdlr/reqpool/__init__.py
cmdlr/reqpool/hostpool.py
cmdlr/reqpool/req.py
cmdlr/reqpool/reqpool.py
cmdlr/reqpool/sesspool.py
cmdlr-4.1.7.dist-info/LICENSE
cmdlr-4.1.7.dist-info/METADATA
cmdlr-4.1.7.dist-info/WHEEL
cmdlr-4.1.7.dist-info/entry_points.txt
cmdlr-4.1.7.dist-info/top_level.txt
cmdlr-4.1.7.dist-info/RECORD
