Metadata-Version: 2.1
Name: cmdlr
Version: 4.1.7
Summary: Extensible comic subscriber.
Home-page: https://github.com/visig9/cmdlr
Author: visig
Author-email: visig@protonmail.ch
License: MIT
Platform: UNKNOWN
Classifier: Programming Language :: Python :: 3
Classifier: Programming Language :: Python :: 3.5
Classifier: Programming Language :: Python :: 3.6
Classifier: Environment :: Console
Classifier: Operating System :: POSIX :: Linux
Classifier: Topic :: System :: Archiving
Requires-Dist: pyyaml (<5,>=4.2b1)
Requires-Dist: aiohttp (<4,>=3)
Requires-Dist: aiohttp-socks (==0.2)
Requires-Dist: voluptuous (<0.12,>=0.11.5)
Requires-Dist: wcwidth (==0.1.7)
Requires-Dist: beautifulsoup4
Requires-Dist: fake-useragent (==0.1.11)
